cleangpt/__init__.py
cleangpt/helpers.py
cleangpt/main.py
cleangpt-0.1.2.dist-info/METADATA
cleangpt-0.1.2.dist-info/WHEEL
cleangpt-0.1.2.dist-info/entry_points.txt
cleangpt-0.1.2.dist-info/top_level.txt
cleangpt-0.1.2.dist-info/RECORD
