Metadata-Version: 2.1
Name: cleangpt
Version: 0.1.2
Summary: CLI to make AI-generated text more human-like.
Home-page: https://github.com/technoabsurdist/cleangpt
Author: Emilio Andere
Author-email: andere.emi@gmail.com
License: UNKNOWN
Platform: UNKNOWN
Classifier: Development Status :: 3 - Alpha
Classifier: Intended Audience :: Developers
Classifier: License :: OSI Approved :: MIT License
Classifier: Programming Language :: Python :: 3
Classifier: Programming Language :: Python :: 3.6
Classifier: Programming Language :: Python :: 3.7
Classifier: Programming Language :: Python :: 3.8
Classifier: Programming Language :: Python :: 3.9
Requires-Python: >=3.6
Requires-Dist: aiohttp (>=3.8.4)
Requires-Dist: aiosignal (>=1.3.1)
Requires-Dist: async-timeout (>=4.0.2)
Requires-Dist: numpy (>=1.24.2)
Requires-Dist: openai (>=0.27.4)
